mifs/__init__.py
mifs/mi.py
mifs/mifs.py
mifs/setup.py
mifs/version.py
mifs/doc/conf.py
mifs/doc/examples.py
mifspy-0.0.1b3.dist-info/LICENSE
mifspy-0.0.1b3.dist-info/METADATA
mifspy-0.0.1b3.dist-info/WHEEL
mifspy-0.0.1b3.dist-info/top_level.txt
mifspy-0.0.1b3.dist-info/RECORD
