Metadata-Version: 2.2
Name: mifspy
Version: 0.0.1b3
Summary: Parallelized Mutual Information based Feature Selection module.
Author-email: "D. Homola" <dani.homola@gmail.com>
Project-URL: Homepage, https://github.com/danielhomola/mifs
Project-URL: Bug Tracker, https://github.com/danielhomola/mifs/issues
Project-URL: Upload Page, https://github.com/Caewinix/mifspy
Classifier: Intended Audience :: Science/Research
Classifier: Intended Audience :: Developers
Classifier: License :: OSI Approved
Classifier: Programming Language :: C
Classifier: Programming Language :: Python
Classifier: Topic :: Software Development
Classifier: Topic :: Scientific/Engineering
Classifier: Programming Language :: Python :: 2.7
Classifier: Programming Language :: Python :: 3.5
Classifier: Operating System :: OS Independent
Requires-Python: >=3.5
License-File: LICENSE
Requires-Dist: scipy>=0.17.0
Requires-Dist: numpy>=1.10.4
Requires-Dist: scikit-learn>=0.17.1
Requires-Dist: bottleneck>=1.0.0
Requires-Dist: joblib>=0.16.0
Requires-Dist: pandas
